paiutils/__init__.py
paiutils/analytics.py
paiutils/audio.py
paiutils/autoencoder.py
paiutils/evolution_algorithm.py
paiutils/gan.py
paiutils/image.py
paiutils/neural_network.py
paiutils/reinforcement.py
paiutils/reinforcement_agents.py
paiutils/util_funcs.py
paiutils/sox/libflac-8.dll
paiutils/sox/libgcc_s_sjlj-1.dll
paiutils/sox/libgomp-1.dll
paiutils/sox/libid3tag-0.dll
paiutils/sox/libmad-0.dll
paiutils/sox/libmp3lame-0.dll
paiutils/sox/libogg-0.dll
paiutils/sox/libpng16-16.dll
paiutils/sox/libsox-3.dll
paiutils/sox/libssp-0.dll
paiutils/sox/libvorbis-0.dll
paiutils/sox/libvorbisenc-2.dll
paiutils/sox/libvorbisfile-3.dll
paiutils/sox/libwavpack-1.dll
paiutils/sox/libwinpthread-1.dll
paiutils/sox/sox.exe
paiutils/sox/wget.exe
paiutils/sox/wget.ini
paiutils/sox/zlib1.dll
tests/__init__.py
tests/test_analytics.py
tests/test_audio.py
tests/test_autoencoder.py
tests/test_evolution_algorithm.py
tests/test_gan.py
tests/test_image.py
tests/test_neural_network.py
tests/test_reinforcement.py
tests/test_reinforcement_agents.py
tests/test_util_funcs.py
paiutils-4.0.0.dist-info/LICENSE
paiutils-4.0.0.dist-info/METADATA
paiutils-4.0.0.dist-info/WHEEL
paiutils-4.0.0.dist-info/top_level.txt
paiutils-4.0.0.dist-info/RECORD
