Metadata-Version: 2.1
Name: paiutils
Version: 4.0.0
Summary: An artificial intelligence utilities package built to remove the delays of machine learning research.
Home-page: https://github.com/Tiger767/PAI-Utils
Author: Travis Hammond
License: UNKNOWN
Platform: UNKNOWN
Classifier: Programming Language :: Python :: 3
Classifier: License :: OSI Approved :: MIT License
Classifier: Topic :: Scientific/Engineering
Requires-Python: >=3.7
Requires-Dist: numpy (>=1)
Requires-Dist: h5py (>=2)
Requires-Dist: matplotlib (>=3)
Requires-Dist: scikit-learn
Requires-Dist: opencv-python (>=4)
Provides-Extra: gym
Requires-Dist: gym (>=0.17.1) ; extra == 'gym'
Provides-Extra: pa
Requires-Dist: pyaudio (>=0.2) ; extra == 'pa'
Provides-Extra: tf
Requires-Dist: tensorflow (>=2.1) ; extra == 'tf'
Provides-Extra: tf_gpu
Requires-Dist: tensorflow-gpu (>=2.1) ; extra == 'tf_gpu'
Provides-Extra: tfp
Requires-Dist: tensorflow-probability (>=0.11.1) ; extra == 'tfp'
Provides-Extra: wv
Requires-Dist: webrtcvad (>=2.0) ; extra == 'wv'
